scmidas/__init__.py
scmidas/config.py
scmidas/data.py
scmidas/model.py
scmidas/nn.py
scmidas/utils.py
scmidas-0.1.13.dist-info/LICENSE
scmidas-0.1.13.dist-info/METADATA
scmidas-0.1.13.dist-info/WHEEL
scmidas-0.1.13.dist-info/top_level.txt
scmidas-0.1.13.dist-info/RECORD
